pattools/__init__.py
pattools/io.py
pattools/matrixgenerate.py
pattools/motif.py
pattools/pat.py
pattools/region.py
pattools/beta/__init__.py
pattools/beta/beta.py
pattools/deconv/__init__.py
pattools/deconv/optimization.py
pattools/deconv/utils.py
pattools/deconv/loyfer/Atlas.U25.l4.hg19.full.tsv
pattools/deconv/loyfer/Atlas.U25.l4.hg19.tsv
pattools/deconv/loyfer/Atlas.U25.l4.hg38.full.tsv
pattools/deconv/loyfer/Atlas.U25.l4.hg38.tsv
pattools/deconv/loyfer/Atlas.U250.l4.hg19.full.tsv
pattools/deconv/loyfer/Atlas.U250.l4.hg19.tsv
pattools/deconv/loyfer/Atlas.U250.l4.hg38.full.tsv
pattools/deconv/loyfer/__init__.py
pattools/deconv/loyfer/loyfer.py
pattools/deconv/moss/__init__.py
pattools/deconv/moss/marker.csv
pattools/deconv/moss/moss.py
pattools/deconv/sun/__init__.py
pattools/deconv/sun/markerType1.csv
pattools/deconv/sun/markerType2.csv
pattools/deconv/sun/sun.py
pattools/entropy/__init__.py
pattools/entropy/entropy.py
pattools/format/__init__.py
pattools/format/pat2motif.py
pattools/vector/__init__.py
pattools/vector/calculator.py
pattools/vector/diff.py
pattools/vector/vector.py
pattools/vector/window.py
pattools_methy-0.1.0.dist-info/LICENSE
pattools_methy-0.1.0.dist-info/METADATA
pattools_methy-0.1.0.dist-info/WHEEL
pattools_methy-0.1.0.dist-info/entry_points.txt
pattools_methy-0.1.0.dist-info/top_level.txt
pattools_methy-0.1.0.dist-info/RECORD
